mat_vertica/__init__.py
mat_vertica-0.0.2.dist-info/METADATA
mat_vertica-0.0.2.dist-info/WHEEL
mat_vertica-0.0.2.dist-info/licenses/LICENSE
mat_vertica-0.0.2.dist-info/RECORD
