Metadata-Version: 2.1
Name: mat_vertica
Version: 0.0.2
Summary: https://gitlab.com/lucas.larroque/mat-lib/-/blob/main/mat_vertica/README.md
Project-URL: Homepage, https://gitlab.com/lucas.larroque/mat-lib/-/blob/main/mat_vertica
Project-URL: Bug Tracker, https://gitlab.com/lucas.larroque/mat-lib/-/issues
Author-email: lucas <lucas.larroque@iquall.net>
License: MIT License
License-File: LICENSE
Classifier: License :: OSI Approved :: MIT License
Classifier: Operating System :: OS Independent
Classifier: Programming Language :: Python :: 3
Requires-Python: >=3.8
Requires-Dist: vertica-python>=1.3
